cocotb_yaml_runner/__init__.py
cocotb_yaml_runner/cli.py
cocotb_yaml_runner/module_runner.py
cocotb_yaml_runner-0.1.0.dist-info/METADATA
cocotb_yaml_runner-0.1.0.dist-info/WHEEL
cocotb_yaml_runner-0.1.0.dist-info/entry_points.txt
cocotb_yaml_runner-0.1.0.dist-info/top_level.txt
cocotb_yaml_runner-0.1.0.dist-info/RECORD
